flumes_django/__init__.py
flumes_django/admin.py
flumes_django/apps.py
flumes_django/config.py
flumes_django/forms.py
flumes_django/managers.py
flumes_django/models.py
flumes_django/router.py
flumes_django/static/admin/flume_django/common/topology.css
flumes_django/templates/admin/flumes_django/file/change_list.html
flumes_django/templates/admin/flumes_django/file/upload.html
flumes_django/templates/admin/flumes_django/info/streams.html
flumes_django/templates/admin/flumes_django/stream/children.html
flumes_django/templates/flumes_django/templatetags/children.html
flumes_django/templatetags/__init__.py
flumes_django/templatetags/topology.py
flumes_django/tests/__init__.py
flumes_django-0.1.0.dist-info/LICENSE.LGPL
flumes_django-0.1.0.dist-info/WHEEL
flumes_django-0.1.0.dist-info/METADATA
flumes_django-0.1.0.dist-info/RECORD
