Metadata-Version: 2.1
Name: flumes-django
Version: 0.1.0
Summary: 
Author: Jorge Zapata
Author-email: jorgeluis.zapata@gmail.com
Requires-Python: >=3.9,<4.0
Classifier: Programming Language :: Python :: 3
Classifier: Programming Language :: Python :: 3.10
Classifier: Programming Language :: Python :: 3.9
Requires-Dist: Django (>=2.2,<4.0)
Requires-Dist: flumes (>=0.1.3,<0.2.0)
